zabbi/__init__.py
zabbi/fcall.py
zabbi-0.3.dist-info/LICENSE
zabbi-0.3.dist-info/METADATA
zabbi-0.3.dist-info/WHEEL
zabbi-0.3.dist-info/top_level.txt
zabbi-0.3.dist-info/RECORD
