Metadata-Version: 2.1
Name: zabbi
Version: 0.3
Summary: Zabbix Python API Module
Home-page: https://github.com/VipsSharma/Zabbix.git
Author: Vipul Sharma
Author-email: sharma.vips5512@gmail.com
License: UNKNOWN
Platform: UNKNOWN
Classifier: Programming Language :: Python :: 2.7
Classifier: Programming Language :: Python :: 3
Classifier: License :: OSI Approved :: MIT License
Classifier: Operating System :: OS Independent
